viame2coco/__init__.py
viame2coco/viame2coco.py
viame2coco/viame_manual_annotations.py
viame2coco/vid_utils.py
viame2coco-0.2.0.dist-info/licenses/LICENSE
viame2coco-0.2.0.dist-info/WHEEL
viame2coco-0.2.0.dist-info/METADATA
viame2coco-0.2.0.dist-info/RECORD
