Metadata-Version: 2.4
Name: viame2coco
Version: 0.2.0
Summary: tools to convert VIAME output to COCO format
Author: CScott Brown
Classifier: Programming Language :: Python :: 3
License-File: LICENSE
Requires-Dist: pycocowriter
Requires-Dist: opencv-python
Requires-Dist: pillow
Requires-Dist: mkdocs ; extra == "dev"
Requires-Dist: mkdocs-material ; extra == "dev"
Requires-Dist: mkdocstrings[python] ; extra == "dev"
Requires-Dist: jupyter ; extra == "dev"
Project-URL: Documentation, https://nodd-tools.github.io/viame2coco/
Project-URL: Source, https://github.com/nodd-tools/viame2coco
Provides-Extra: dev
